composio_togetherai/__init__.py
composio_togetherai/toolset.py
composio_togetherai-0.7.6.dist-info/METADATA
composio_togetherai-0.7.6.dist-info/WHEEL
composio_togetherai-0.7.6.dist-info/top_level.txt
composio_togetherai-0.7.6.dist-info/RECORD
