Metadata-Version: 2.2
Name: composio_togetherai
Version: 0.7.6
Summary: Use Composio to get an array of tools with your Together AI Function Call.
Home-page: https://github.com/ComposioHQ/composio
Author: Composio
Author-email: tech@composio.dev
Classifier: Programming Language :: Python :: 3
Classifier: License :: OSI Approved :: Apache Software License
Classifier: Operating System :: OS Independent
Requires-Python: >=3.9,<4
Requires-Dist: composio_core<0.8.0,>=0.7.0
Requires-Dist: together
Requires-Dist: openai
Dynamic: author
Dynamic: author-email
Dynamic: classifier
Dynamic: description
Dynamic: description-content-type
Dynamic: home-page
Dynamic: requires-dist
Dynamic: requires-python
Dynamic: summary
